django_mitid_auth/__init__.py
django_mitid_auth/apps.py
django_mitid_auth/dummy/__init__.py
django_mitid_auth/dummy/dummy.py
django_mitid_auth/exceptions.py
django_mitid_auth/loginprovider.py
django_mitid_auth/management/__init__.py
django_mitid_auth/management/commands/__init__.py
django_mitid_auth/management/commands/update_mitid_idp_metadata.py
django_mitid_auth/middleware.py
django_mitid_auth/openid/__init__.py
django_mitid_auth/openid/openid.py
django_mitid_auth/openid/urls.py
django_mitid_auth/saml/__init__.py
django_mitid_auth/saml/backend.py
django_mitid_auth/saml/mixins.py
django_mitid_auth/saml/oiosaml.py
django_mitid_auth/saml/oiosaml_attributemaps/__init__.py
django_mitid_auth/saml/oiosaml_attributemaps/attributemap.py
django_mitid_auth/saml/saml2.py
django_mitid_auth/saml/urls.py
django_mitid_auth/saml/views.py
django_mitid_auth/templates/__init__.py
django_mitid_auth/templates/django_mitid_auth/bypass.html
django_mitid_auth/templates/django_mitid_auth/error.html
django_mitid_auth/templates/django_mitid_auth/login_assurance.html
django_mitid_auth/templates/django_mitid_auth/login_no_cprcvr.html
django_mitid_auth/templates/django_mitid_auth/login_repeat.html
django_mitid_auth/templates/django_mitid_auth/login_timeout.html
django_mitid_auth/urls.py
django_mitid_auth/views.py
gl_mitid-1.7.0.dist-info/METADATA
gl_mitid-1.7.0.dist-info/WHEEL
gl_mitid-1.7.0.dist-info/licenses/LICENSE
gl_mitid-1.7.0.dist-info/RECORD
