Metadata-Version: 2.4
Name: gl-mitid
Version: 1.7.0
Summary: MitID middle layer
License-Expression: MPL-2.0
License-File: LICENSE
Author: Magenta ApS
Author-email: info@magenta.dk
Requires-Python: >=3.11,<4.0
Classifier: Programming Language :: Python :: 3
Classifier: Programming Language :: Python :: 3.11
Classifier: Programming Language :: Python :: 3.12
Classifier: Programming Language :: Python :: 3.13
Classifier: Programming Language :: Python :: 3.14
Requires-Dist: django (>=5)
Requires-Dist: pysaml2 (==7.5.4)
Requires-Dist: xmltodict (==1.0.2)
